LICENSE
MANIFEST.in
README.md
setup.cfg
setup.py
django_pusherable.egg-info/PKG-INFO
django_pusherable.egg-info/SOURCES.txt
django_pusherable.egg-info/dependency_links.txt
django_pusherable.egg-info/not-zip-safe
django_pusherable.egg-info/requires.txt
django_pusherable.egg-info/top_level.txt
pusherable/__init__.py
pusherable/mixins.py
pusherable/example/__init__.py
pusherable/example/models.py
pusherable/example/urls.py
pusherable/example/views.py
pusherable/example/templates/example.html
pusherable/templatetags/__init__.py
pusherable/templatetags/pusherable_tags.py