Metadata-Version: 1.1
Name: django-pusherable
Version: 0.2.0
Summary: Real time object access notifications via Pusher
Home-page: https://github.com/pusher/django-pusherable
Author: Aaron Bassett, Pusher
Author-email: aaron@rawtech.io, support@pusher.com
License: BSD
Keywords: django-pusherable
Platform: UNKNOWN
Classifier: Framework :: Django
Classifier: Intended Audience :: Developers
Classifier: License :: OSI Approved :: BSD License
Classifier: Natural Language :: English
Classifier: Programming Language :: Python :: 2
Classifier: Programming Language :: Python :: 2.6
Classifier: Programming Language :: Python :: 2.7
